[{"book":"Бытие","number":"10"},{"book":"Исход","number":"20"},{"book":"Левит","number":"30"},{"book":"Числа","number":"40"},{"book":"Втор.","number":"50"},{"book":"Нав.","number":"60"},{"book":"Судей","number":"70"},{"book":"Руфь","number":"80"},{"book":"1Цар.","number":"90"},{"book":"2Цар.","number":"100"},{"book":"3Цар.","number":"110"},{"book":"4Цар.","number":"120"},{"book":"1Пар.","number":"130"},{"book":"2Пар.","number":"140"},{"book":"Ездра","number":"150"},{"book":"Неемия","number":"160"},{"book":"Есфирь","number":"190"},{"book":"Иов","number":"220"},{"book":"Пс.","number":"230"},{"book":"Прит.","number":"240"},{"book":"Еккл.","number":"250"},{"book":"Песн.","number":"260"},{"book":"Исаия","number":"290"},{"book":"Иер.","number":"300"},{"book":"Пл.Иер.","number":"310"},{"book":"Иез.","number":"330"},{"book":"Дан.","number":"340"},{"book":"Осия","number":"350"},{"book":"Иоиль","number":"360"},{"book":"Амос","number":"370"},{"book":"Авдий","number":"380"},{"book":"Иона","number":"390"},{"book":"Михей","number":"400"},{"book":"Наум","number":"410"},{"book":"Аввакум","number":"420"},{"book":"Софония","number":"430"},{"book":"Аггей","number":"440"},{"book":"Зах.","number":"450"},{"book":"Малахия","number":"460"},{"book":"Матфея","number":"470"},{"book":"Марка","number":"480"},{"book":"Луки","number":"490"},{"book":"Иоанна","number":"500"},{"book":"Деяния","number":"510"},{"book":"Иакова","number":"660"},{"book":"1Петра","number":"670"},{"book":"2Петра","number":"680"},{"book":"1Иоанна","number":"690"},{"book":"2Иоанна","number":"700"},{"book":"3Иоанна","number":"710"},{"book":"Иуды","number":"720"},{"book":"Рим.","number":"520"},{"book":"1Кор.","number":"530"},{"book":"2Кор.","number":"540"},{"book":"Гал.","number":"550"},{"book":"Еф.","number":"560"},{"book":"Флп.","number":"570"},{"book":"Кол.","number":"580"},{"book":"1Фес.","number":"590"},{"book":"2Фес.","number":"600"},{"book":"1Тим.","number":"610"},{"book":"2Тим.","number":"620"},{"book":"Титу","number":"630"},{"book":"Филимону","number":"640"},{"book":"Евреям","number":"650"},{"book":"Откр.","number":"730"}]